bee_sdk/__init__.py
bee_sdk/bee.py
beeai/__init__.py
beeai/bee.py
beeai-1.0.1.dist-info/LICENSE
beeai-1.0.1.dist-info/METADATA
beeai-1.0.1.dist-info/WHEEL
beeai-1.0.1.dist-info/top_level.txt
beeai-1.0.1.dist-info/RECORD
